ssepywidget/__init__.py
ssepywidget/_widget.py
ssepywidget/widget.js
ssepyrenderer-0.0.1.dist-info/METADATA
ssepyrenderer-0.0.1.dist-info/WHEEL
ssepyrenderer-0.0.1.dist-info/licenses/LICENSE.txt
ssepyrenderer-0.0.1.dist-info/RECORD
