Metadata-Version: 2.4
Name: ssepyrenderer
Version: 0.0.1
Author-email: temp <temp@example.com>
License-Expression: MIT
License-File: LICENSE.txt
Classifier: Framework :: Jupyter
Classifier: Programming Language :: Python :: 3
Requires-Python: >=3.9
Requires-Dist: anywidget>=0.9.18
Requires-Dist: ipywidgets>=8.1.7
Requires-Dist: traitlets>=5.14.3
